{
  "kind": "collectionType",
  "collectionName": "homepages",
  "info": {
    "singularName": "homepage",
    "pluralName": "homepages",
    "displayName": "Homepage"
  },
  "options": {
    "draftAndPublish": true
  },
  "pluginOptions": {
    "i18n": {
      "localized": true
    }
  },
  "attributes": {
    "title": {
      "pluginOptions": {
        "i18n": {
          "localized": true
        }
      },
      "type": "string",
      "required": true
    },
    "description": {
      "pluginOptions": {
        "i18n": {
          "localized": true
        }
      },
      "type": "text",
      "required": true
    },
    "components": {
      "pluginOptions": {
        "i18n": {
          "localized": true
        }
      },
      "type": "dynamiczone",
      "components": ["ui.hero"],
      "required": true,
      "min": 1
    },
    "site": {
      "pluginOptions": {
        "i18n": {
          "localized": true
        }
      },
      "type": "enumeration",
      "enum": ["cloud", "dotnet"],
      "required": true,
      "default": "dotnet"
    }
  }
}
